texrocket/__init__.py
texrocket/main.py
texrocket-0.0.9.dist-info/LICENSE
texrocket-0.0.9.dist-info/METADATA
texrocket-0.0.9.dist-info/WHEEL
texrocket-0.0.9.dist-info/entry_points.txt
texrocket-0.0.9.dist-info/top_level.txt
texrocket-0.0.9.dist-info/RECORD
