Metadata-Version: 2.1
Name: texrocket
Version: 0.0.9
Summary: A minimal LaTeX template engine.
Home-page: https://github.com/albertomosconi/texrocket
Author: Alberto Mosconi
Author-email: albertomaria.mosconi@gmail.com
License: UNKNOWN
Project-URL: Bug Tracker, https://github.com/albertomosconi/texrocket/issues
Platform: UNKNOWN
Classifier: Programming Language :: Python :: 3
Classifier: License :: OSI Approved :: GNU General Public License v3 (GPLv3)
Classifier: Operating System :: OS Independent
Classifier: Topic :: Text Processing :: Markup :: LaTeX
Requires-Python: >=3.6
License-File: LICENSE
